pycolims/__init__.py
pycolims/menus/Menu_Factory.py
pycolims/menus/__init__.py
pycolims/menus/_base_menu_template.py
pycolims/menus/_menu_engine.py
pycolims/menus/_menu_multi.py
pycolims/menus/_menu_single.py
pycolims/menus/customtypes/__init__.py
pycolims/menus/customtypes/_cremental_list.py
pycolims/menus/data/__init__.py
pycolims/menus/data/_command.py
pycolims/menus/data/_pages.py
pycolims/menus/data/_terminal.py
pycolims/menus/data/_work.py
pycolims/menus/data/data_factory.py
pycolims-0.2.0.dist-info/LICENSE
pycolims-0.2.0.dist-info/METADATA
pycolims-0.2.0.dist-info/WHEEL
pycolims-0.2.0.dist-info/top_level.txt
pycolims-0.2.0.dist-info/RECORD
