Metadata-Version: 2.1
Name: pycolims
Version: 0.2.0
Summary: An importable, single stage CLI menu package
Home-page: https://github.com/dpazavalos/pycolims
Author: Daniel Paz Avalos
Author-email: dpazavalos@protonmail.com
License: UNKNOWN
Platform: UNKNOWN
Classifier: Programming Language :: Python :: 3.5
Classifier: License :: OSI Approved :: MIT License
Classifier: Operating System :: OS Independent
